bs_repoman/__init__.py
bs_repoman/config.py
bs_repoman/constants.py
bs_repoman/gh_templates.py
bs_repoman/log.py
bs_repoman/scripts/__init__.py
bs_repoman/scripts/repoman.py
bs_repoman-0.2.0.data/scripts/repoman.py
bs_repoman-0.2.0.dist-info/LICENSE
bs_repoman-0.2.0.dist-info/METADATA
bs_repoman-0.2.0.dist-info/WHEEL
bs_repoman-0.2.0.dist-info/entry_points.txt
bs_repoman-0.2.0.dist-info/top_level.txt
bs_repoman-0.2.0.dist-info/RECORD
